plover_cat/TextEditor.py
plover_cat/__init__.py
plover_cat/main_window.py
plover_cat/plover_cat_ui.py
plover_cat/project.py
plover_cat/resources_rc.py
plover_cat/steno_to_stroke.py
plover_cat/translate.py
plover_cat-0.1.3.dist-info/DESCRIPTION.rst
plover_cat-0.1.3.dist-info/METADATA
plover_cat-0.1.3.dist-info/RECORD
plover_cat-0.1.3.dist-info/WHEEL
plover_cat-0.1.3.dist-info/entry_points.txt
plover_cat-0.1.3.dist-info/metadata.json
plover_cat-0.1.3.dist-info/top_level.txt
plover_cat-0.1.3.dist-info/zip-safe
