Metadata-Version: 2.0
Name: plover-cat
Version: 0.1.3
Summary: A CAT software for Plover
Home-page: https://github.com/LukeSilva/plover_cat
Author: Luke Silva
Author-email: plovercat@lukesilva.com
License: MIT
Keywords: plover plover_plugin
Platform: UNKNOWN
Classifier: Development Status :: 4 - Beta
Classifier: Environment :: Plugins
Classifier: Intended Audience :: End Users/Desktop
Classifier: License :: OSI Approved :: MIT License
Classifier: Operating System :: OS Independent
Classifier: Programming Language :: Python :: 3
Classifier: Programming Language :: Python :: 3.4
Classifier: Programming Language :: Python :: 3.5
Classifier: Programming Language :: Python :: 3.6
Requires-Dist: plover (>=4.0.0.dev8)
